{
  "name": "毛概复习资料（参考题）",
  "questions": [
    {
      "type": "qa",
      "category": "单选题",
      "question": "马克思主义中国化时代化的最新理论成果是",
      "answer": "习近平新时代中国特色社会主义思想"
    },
    {
      "type": "qa",
      "category": "单选题",
      "question": "新民主主义革命的主力军是",
      "answer": "农民（贫雇农）"
    },
    {
      "type": "qa",
      "category": "单选题",
      "question": "建设新型人民军队的根本原则是",
      "answer": "党对军队的绝对领导（党指挥枪）"
    },
    {
      "type": "qa",
      "category": "单选题",
      "question": "新民主主义社会属于",
      "answer": "属于社会主义体系的过渡性质的社会"
    },
    {
      "type": "qa",
      "category": "单选题",
      "question": "和平赎买政策的主要实施对象是",
      "answer": "民族资产阶级（资本主义工商业）"
    },
    {
      "type": "qa",
      "category": "单选题",
      "question": "（）正式提出\"邓小平理论\"这一概念",
      "answer": "党的十五大（中国共产党第十五次全国代表大会）"
    },
    {
      "type": "qa",
      "category": "单选题",
      "question": "\"一个党，一个国家，一个民族，如果一切从本本出发，思想僵化，迷信盛行，那它就不能前进，它的生机就停止了，就要亡党亡国。\"这句话要表达的是",
      "answer": "坚持解放思想、实事求是"
    },
    {
      "type": "qa",
      "category": "单选题",
      "question": "社会主义的根本任务是",
      "answer": "解放和发展社会生产力"
    },
    {
      "type": "qa",
      "category": "单选题",
      "question": "科学发展观的基本要求是",
      "answer": "全面协调可持续"
    },
    {
      "type": "qa",
      "category": "单选题",
      "question": "党执政兴国的第一要务是",
      "answer": "发展"
    },
    {
      "type": "qa",
      "category": "单选题",
      "question": "科学发展观的核心立场是",
      "answer": "以人为本"
    },
    {
      "type": "qa",
      "category": "简答题",
      "question": "新民主主义经济纲领主要内容包括",
      "answer": "①没收封建地主阶级的土地归农民所有；②没收以四大家族为首的官僚垄断资本归新民主主义国家所有；③保护民族工商业。"
    },
    {
      "type": "qa",
      "category": "简答题",
      "question": "正确处理人民内部矛盾的方针包括",
      "answer": "总方针：团结—批评—团结；\n共产党与民主党派：长期共存、互相监督；\n科学文化领域：百花齐放、百家争鸣；\n经济领域：统筹兼顾、适当安排，兼顾国家、集体、个人三者利益；\n民族关系：民族平等、民族团结、民族区域自治。"
    },
    {
      "type": "qa",
      "category": "简答题",
      "question": "邓小平社会主义市场经济理论的主要观点有",
      "answer": "①计划经济不等于社会主义，市场经济不等于资本主义，计划和市场都只是经济手段，不是社会主义与资本主义的本质区别；\n②社会主义也可以搞市场经济，市场经济可以为社会主义服务；\n③计划和市场可以结合使用，要把计划调节与市场调节结合起来，解放和发展生产力。"
    },
    {
      "type": "qa",
      "category": "简答题",
      "question": "社会主义初级阶段的含义包括",
      "answer": "①我国社会已经是社会主义社会，必须坚持社会主义，不能偏离社会主义发展方向；\n②我国的社会主义还处在初级阶段，必须立足生产力落后、商品经济不发达的客观实际，不能超越这个发展阶段。"
    },
    {
      "type": "qa",
      "category": "简答题",
      "question": "马克思主义中国化时代化的理论成果的关系",
      "answer": "①一脉相承：全部理论成果都坚持马克思主义立场、观点、方法，坚守共产主义远大理想，统一于马克思主义基本原理同中国具体实际、中华优秀传统文化相结合的实践进程。\n②与时俱进：立足不同历史时期的时代课题、历史任务，在继承前人理论的基础上不断创新发展，先后实现马克思主义中国化时代化三次历史性飞跃。\n③统一整体、层层递进：毛泽东思想是第一次历史性飞跃；邓小平理论、\"三个代表\"重要思想、科学发展观属于中国特色社会主义理论体系，实现新的飞跃；习近平新时代中国特色社会主义思想是当代中国马克思主义、二十一世纪马克思主义，实现新的飞跃，是最新理论成果，既继承前面所有成果，又作出原创性理论创新。\n④所有成果都是党集体智慧的结晶，共同指引中国革命、建设、改革、新时代伟大事业不断前进。"
    },
    {
      "type": "qa",
      "category": "简答题",
      "question": "毛泽东思想活的灵魂是",
      "answer": "实事求是、群众路线、独立自主"
    },
    {
      "type": "choice",
      "category": "判断题",
      "question": "解放思想的目的归根到底是为了实事求是。",
      "options": [
        "正确",
        "错误"
      ],
      "answer": 0
    },
    {
      "type": "choice",
      "category": "判断题",
      "question": "社会主义初级阶段不是任何国家进入社会主义都要经历的起始阶段。",
      "options": [
        "正确",
        "错误"
      ],
      "answer": 0
    },
    {
      "type": "choice",
      "category": "判断题",
      "question": "依法治国是党领导人民治理国家的基本方略。",
      "options": [
        "正确",
        "错误"
      ],
      "answer": 0
    },
    {
      "type": "qa",
      "category": "问答题",
      "question": "邓小平理论回答的基本问题是",
      "answer": "什么是社会主义、怎样建设社会主义"
    },
    {
      "type": "qa",
      "category": "问答题",
      "question": "\"三个代表\"重要思想回答的基本问题是",
      "answer": "建设什么样的党、怎样建设党"
    },
    {
      "type": "qa",
      "category": "问答题",
      "question": "科学发展观回答的基本问题是",
      "answer": "实现什么样的发展、怎样发展"
    },
    {
      "type": "qa",
      "category": "问答题",
      "question": "习近平新时代中国特色社会主义思想回答的基本问题是",
      "answer": "新时代坚持和发展什么样的中国特色社会主义、怎样坚持和发展中国特色社会主义，建设什么样的社会主义现代化强国、怎样建设社会主义现代化强国，建设什么样的长期执政的马克思主义政党、怎样建设长期执政的马克思主义政党等重大时代课题。"
    },
    {
      "type": "qa",
      "category": "问答题",
      "question": "毛泽东思想的主要内容",
      "answer": "①新民主主义革命理论\n②社会主义革命和社会主义建设理论\n③革命军队建设和军事战略理论\n④政策和策略理论\n⑤思想政治工作和文化工作理论\n⑥党的建设理论"
    },
    {
      "type": "qa",
      "category": "问答题",
      "question": "党在过渡时期是如何对个体农业进行社会主义改造的？",
      "answer": "第一，积极引导农民组织起来，走互助合作道路。\n第二，遵循自愿互利、典型示范和国家帮助的原则。\n第三，正确分析农村的阶级和阶层状况，制定正确的阶级政策。\n第四，坚持积极领导、稳步前进的方针，采取循序渐进的步骤，农业社会主义改造大体上经历了互助组、初级社和高级社三个发展阶段。"
    },
    {
      "type": "qa",
      "category": "问答题",
      "question": "党在社会主义初级阶段的基本路线",
      "answer": "领导和团结全国各族人民，以经济建设为中心，坚持四项基本原则，坚持改革开放，自力更生，艰苦创业，为把我国建设成为富强民主文明和谐美丽的社会主义现代化强国而奋斗。（简称：一个中心，两个基本点）"
    },
    {
      "type": "qa",
      "category": "问答题",
      "question": "科学发展观的主要内容",
      "answer": "第一要义是发展；核心立场是以人为本；基本要求是全面协调可持续；根本方法是统筹兼顾。"
    },
    {
      "type": "qa",
      "category": "问答题",
      "question": "毛泽东思想活的灵魂（详细）",
      "answer": "实事求是：一切从实际出发，理论联系实际，在实践中检验和发展真理。\n群众路线：一切为了群众，一切依靠群众，从群众中来，到群众中去。\n独立自主：立足本国实际，依靠本国人民力量，走自己的路。"
    },
    {
      "type": "qa",
      "category": "问答题",
      "question": "新民主主义革命总路线",
      "answer": "无产阶级领导的，人民大众的，反对帝国主义、封建主义和官僚资本主义的革命。"
    },
    {
      "type": "qa",
      "category": "问答题",
      "question": "三大改造的内容",
      "answer": "对农业、手工业、资本主义工商业进行社会主义改造。"
    },
    {
      "type": "qa",
      "category": "问答题",
      "question": "新民主主义经济纲领",
      "answer": "①没收封建地主阶级土地归农民所有；\n②没收官僚垄断资本归新民主主义国家所有；\n③保护民族工商业。"
    },
    {
      "type": "qa",
      "category": "问答题",
      "question": "社会主义市场经济理论的内容",
      "answer": "①计划经济、市场经济都只是经济调节手段，不属于社会制度属性，不是社会主义与资本主义的本质区别；\n②社会主义也可以搞市场经济；\n③计划和市场可以结合，要把计划调节与市场调节结合起来，解放发展生产力。"
    },
    {
      "type": "qa",
      "category": "问答题",
      "question": "马克思主义中国化时代化的理论成果",
      "answer": "①毛泽东思想\n②邓小平理论\n③\"三个代表\"重要思想\n④科学发展观\n⑤习近平新时代中国特色社会主义思想"
    },
    {
      "type": "qa",
      "category": "问答题",
      "question": "论述以毛泽东为代表的中国共产党人初步探索社会主义建设道路的主要理论成果及初步探索的意义。",
      "answer": "【主要理论成果】\n1.调动一切积极因素为社会主义事业服务的思想。这是《论十大关系》确定的基本方针。\n2.正确认识和处理社会主义社会矛盾的思想。毛泽东在《关于正确处理人民内部矛盾的问题》的报告，系统论述了社会主义社会矛盾的理论。包括关于社会主义社会的基本矛盾，关于我国社会的主要矛盾和根本任务，关于社会主义社会两类不同性质的矛盾。\n3.走中国工业化道路的思想。强调要正确处理重工业、轻工业和农业的关系，走一条有别于苏联的中国工业化道路。\n4.初步探索的其他理论成果。\n\n【初步探索的意义】\n1.巩固和发展了我国的社会主义制度。\n2.为开创中国特色社会主义提供了宝贵经验、理论准备和物质基础。\n3.丰富了科学社会主义的理论和实践。"
    },
    {
      "type": "qa",
      "category": "问答题",
      "question": "论述如何建设社会主义政治文明？",
      "answer": "1.建设社会主义政治文明，最根本的就是要坚持党的领导、人民当家作主和依法治国的有机统一。\n2.建设社会主义政治文明，必须发展社会主义民主。\n3.建设社会主义政治文明，必须坚持和完善中国特色社会主义政治制度。\n4.建设社会主义政治文明，必须坚持依法治国。\n5.建设社会主义政治文明，必须进行政治体制改革。\n6.建设社会主义政治文明，必须推进决策的科学化民主化。\n7.建设社会主义政治文明，必须尊重和保障人权。"
    },
    {
      "type": "qa",
      "category": "问答题",
      "question": "中国革命新道路是什么？为什么必须走这条道路？为什么能走这条道路？",
      "answer": "【道路】农村包围城市、武装夺取政权。\n\n【为什么必须走】在半殖民地半封建的中国社会，内无民主制度受封建主义的压迫，外无民族独立而受帝国主义的压迫。中国无产阶级根本没有从事和平、合法斗争的条件，中国革命的主要斗争形式只能是武装斗争。同时，农民占全国人口的绝大多数，是无产阶级可靠的同盟军和主力军，必须深入农村，解决农民的土地问题，发动和武装农民。\n\n【为什么能走】第一，中国社会政治经济发展极端不平衡，军阀割据，存在统治的薄弱环节；第二，广大农村深受压迫，人民革命愿望强烈，群众基础好；第三，全国革命形势继续向前发展；第四，相当力量正式红军的存在；第五，党的领导的有力量及其政策的不错误。"
    }
  ]
}
